pipecaster/__init__.py
pipecaster/channel_scoring.py
pipecaster/channel_selection.py
pipecaster/config.py
pipecaster/cross_validation.py
pipecaster/ensemble_learning.py
pipecaster/multichannel_pipeline.py
pipecaster/parallel.py
pipecaster/ray_backend.py
pipecaster/score_selection.py
pipecaster/testing_utils.py
pipecaster/transform_wrappers.py
pipecaster/utils.py
pipecaster-0.3a0.dist-info/LICENSE
pipecaster-0.3a0.dist-info/METADATA
pipecaster-0.3a0.dist-info/WHEEL
pipecaster-0.3a0.dist-info/top_level.txt
pipecaster-0.3a0.dist-info/RECORD
