Metadata-Version: 2.1
Name: pipecaster
Version: 0.3a0
Summary: multichannel machine learning library with in-pipeline automation
Home-page: https://github.com/ajcallegari/pipecaster
Author: A. John Callegari Jr.
Author-email: a.john.callegari@gmail.com
License: MIT
Download-URL: https://github.com/ajcallegari/pipecaster/archive/refs/tags/v0.3-alpha.tar.gz
Keywords: machine learning,semi-auto-ml,multichannel pipeline,workflow automation,ensemble learning,machine learning pipeline
Platform: UNKNOWN
